asciimage/__init__.py
asciimage/asciimage.py
asciimage-3.1415926535.dist-info/LICENSE.txt
asciimage-3.1415926535.dist-info/METADATA
asciimage-3.1415926535.dist-info/WHEEL
asciimage-3.1415926535.dist-info/top_level.txt
asciimage-3.1415926535.dist-info/RECORD
