Metadata-Version: 2.1
Name: asciimage
Version: 3.1415926535
Summary: ASCII art Python library
Home-page: https://github.com/jojo96/asciimage
Author: Ujjayanta
Author-email: ujjayanta.bhaumik.18@ucl.ac.uk
License: MIT
Platform: UNKNOWN
Classifier: Intended Audience :: Developers
Classifier: License :: OSI Approved :: MIT License
Classifier: Programming Language :: Python
Classifier: Programming Language :: Python :: 3
Classifier: Programming Language :: Python :: 3.6
Classifier: Programming Language :: Python :: 3.7
Classifier: Programming Language :: Python :: 3.8
Classifier: Programming Language :: Python :: 3.9
Classifier: Operating System :: OS Independent
Requires-Dist: Pillow
Requires-Dist: docx
